ease_lonlat/__init__.py
ease_lonlat/ease_lonlat.py
ease_lonlat-0.0.3.5.dist-info/LICENSE
ease_lonlat-0.0.3.5.dist-info/METADATA
ease_lonlat-0.0.3.5.dist-info/WHEEL
ease_lonlat-0.0.3.5.dist-info/top_level.txt
ease_lonlat-0.0.3.5.dist-info/RECORD
