Metadata-Version: 2.1
Name: ease-lonlat
Version: 0.0.3.5
Summary: To convert between LON, LAT coordinates and EASE(2) grid ROW, COL.
Home-page: https://github.com/CzendaZdenda/ease_lonlat
Author: Zdenek Ruzicka
Author-email: tramtara@seznam.cz
Project-URL: Bug Tracker, https://github.com/CzendaZdenda/ease_lonlat/issues
Classifier: Programming Language :: Python :: 3
Classifier: License :: OSI Approved :: MIT License
Classifier: Operating System :: OS Independent
Classifier: Topic :: Scientific/Engineering :: GIS
Requires-Python: >=3.6
License-File: LICENSE
Requires-Dist: pyproj
Provides-Extra: testing
Requires-Dist: pytest ; extra == 'testing'
Requires-Dist: numpy ; extra == 'testing'
